printnodeapi/__init__.py
printnodeapi/accounts.py
printnodeapi/auth.py
printnodeapi/computers.py
printnodeapi/gateway.py
printnodeapi/model.py
printnodeapi/util.py
PrintNodeApi-0.2.0.dist-info/LICENSE
PrintNodeApi-0.2.0.dist-info/METADATA
PrintNodeApi-0.2.0.dist-info/WHEEL
PrintNodeApi-0.2.0.dist-info/top_level.txt
PrintNodeApi-0.2.0.dist-info/RECORD
