Metadata-Version: 1.0
Name: PrintNodeApi
Version: 0.2.0
Summary: Python Client for PrintNode's API
Home-page: UNKNOWN
Author: printnode
Author-email: support@printnode.com
License: UNKNOWN
Platform: UNKNOWN
